Metadata-Version: 2.1
Name: pillowcover-gui
Version: 1.2.0
Summary: Easily Manipulate Images Using Python: Change Brightness, Contrast, Sharpness, Resize
Home-page: https://github.com/jotyGill/pillowcover
Author: JGill
Author-email: joty@mygnu.org
License: GNU General Public License v3 or later (GPLv3+)
Keywords: images,image-minipulation
Platform: GNU/Linux
Platform: Ubuntu
Platform: Debian
Platform: Kali
Platform: CentOS
Platform: Arch
Platform: Fedora
Classifier: Intended Audience :: End Users/Desktop
Classifier: Intended Audience :: System Administrators
Classifier: Topic :: Utilities
Classifier: License :: OSI Approved :: GNU General Public License v3 or later (GPLv3+)
Classifier: Natural Language :: English
Classifier: Operating System :: POSIX :: Linux
Classifier: Programming Language :: Python :: 3 :: Only
Classifier: Programming Language :: Python :: 3.5
Classifier: Programming Language :: Python :: 3.6
Requires-Python: >=3.5
